Workbook

Sheet Empresa
A1: Empresa | B1: Ticker | C1: Mês e ano | D1: Operação | E1: Qtd movimentada | F1: Preço médio (R$) | G1: Valor total (R$)
A2: Mater Dei | B2: MATD3 | C2: 46266 | D2: Compra | E2: =SUMIFS(Detalhe!$J:$J,Detalhe!$D:$D,"Empresa",Detalhe!$B:$B,$B2,Detalhe!$C:$C,$C2,Detalhe!$H:$H,$D2,Detalhe!$F:$F,"Ações") | F2: =IF(E2=0,0,G2/E2) | G2: =SUMIFS(Detalhe!$L:$L,Detalhe!$D:$D,"Empresa",Detalhe!$B:$B,$B2,Detalhe!$C:$C,$C2,Detalhe!$H:$H,$D2,Detalhe!$F:$F,"Ações")
A3: Rede D'Or | B3: RDOR3 | C3: 46235 | D3: Compra | E3: =SUMIFS(Detalhe!$J:$J,Detalhe!$D:$D,"Empresa",Detalhe!$B:$B,$B3,Detalhe!$C:$C,$C3,Detalhe!$H:$H,$D3,Detalhe!$F:$F,"Ações") | F3: =IF(E3=0,0,G3/E3) | G3: =SUMIFS(Detalhe!$L:$L,Detalhe!$D:$D,"Empresa",Detalhe!$B:$B,$B3,Detalhe!$C:$C,$C3,Detalhe!$H:$H,$D3,Detalhe!$F:$F,"Ações")
A4: TIM | B4: TIMS3 | C4: 46235 | D4: Compra | E4: =SUMIFS(Detalhe!$J:$J,Detalhe!$D:$D,"Empresa",Detalhe!$B:$B,$B4,Detalhe!$C:$C,$C4,Detalhe!$H:$H,$D4,Detalhe!$F:$F,"Ações") | F4: =IF(E4=0,0,G4/E4) | G4: =SUMIFS(Detalhe!$L:$L,Detalhe!$D:$D,"Empresa",Detalhe!$B:$B,$B4,Detalhe!$C:$C,$C4,Detalhe!$H:$H,$D4,Detalhe!$F:$F,"Ações")
A5: Mater Dei | B5: MATD3 | C5: 46204 | D5: Compra | E5: =SUMIFS(Detalhe!$J:$J,Detalhe!$D:$D,"Empresa",Detalhe!$B:$B,$B5,Detalhe!$C:$C,$C5,Detalhe!$H:$H,$D5,Detalhe!$F:$F,"Ações") | F5: =IF(E5=0,0,G5/E5) | G5: =SUMIFS(Detalhe!$L:$L,Detalhe!$D:$D,"Empresa",Detalhe!$B:$B,$B5,Detalhe!$C:$C,$C5,Detalhe!$H:$H,$D5,Detalhe!$F:$F,"Ações")
A6: Rede D'Or | B6: RDOR3 | C6: 46204 | D6: Compra | E6: =SUMIFS(Detalhe!$J:$J,Detalhe!$D:$D,"Empresa",Detalhe!$B:$B,$B6,Detalhe!$C:$C,$C6,Detalhe!$H:$H,$D6,Detalhe!$F:$F,"Ações") | F6: =IF(E6=0,0,G6/E6) | G6: =SUMIFS(Detalhe!$L:$L,Detalhe!$D:$D,"Empresa",Detalhe!$B:$B,$B6,Detalhe!$C:$C,$C6,Detalhe!$H:$H,$D6,Detalhe!$F:$F,"Ações")
A7: Mater Dei | B7: MATD3 | C7: 46174 | D7: Compra | E7: =SUMIFS(Detalhe!$J:$J,Detalhe!$D:$D,"Empresa",Detalhe!$B:$B,$B7,Detalhe!$C:$C,$C7,Detalhe!$H:$H,$D7,Detalhe!$F:$F,"Ações") | F7: =IF(E7=0,0,G7/E7) | G7: =SUMIFS(Detalhe!$L:$L,Detalhe!$D:$D,"Empresa",Detalhe!$B:$B,$B7,Detalhe!$C:$C,$C7,Detalhe!$H:$H,$D7,Detalhe!$F:$F,"Ações")
A8: Rede D'Or | B8: RDOR3 | C8: 46174 | D8: Compra | E8: =SUMIFS(Detalhe!$J:$J,Detalhe!$D:$D,"Empresa",Detalhe!$B:$B,$B8,Detalhe!$C:$C,$C8,Detalhe!$H:$H,$D8,Detalhe!$F:$F,"Ações") | F8: =IF(E8=0,0,G8/E8) | G8: =SUMIFS(Detalhe!$L:$L,Detalhe!$D:$D,"Empresa",Detalhe!$B:$B,$B8,Detalhe!$C:$C,$C8,Detalhe!$H:$H,$D8,Detalhe!$F:$F,"Ações")
A9: Yduqs | B9: YDUQ3 | C9: 46174 | D9: Compra | E9: =SUMIFS(Detalhe!$J:$J,Detalhe!$D:$D,"Empresa",Detalhe!$B:$B,$B9,Detalhe!$C:$C,$C9,Detalhe!$H:$H,$D9,Detalhe!$F:$F,"Ações") | F9: =IF(E9=0,0,G9/E9) | G9: =SUMIFS(Detalhe!$L:$L,Detalhe!$D:$D,"Empresa",Detalhe!$B:$B,$B9,Detalhe!$C:$C,$C9,Detalhe!$H:$H,$D9,Detalhe!$F:$F,"Ações")
A10: Mater Dei | B10: MATD3 | C10: 46143 | D10: Compra | E10: =SUMIFS(Detalhe!$J:$J,Detalhe!$D:$D,"Empresa",Detalhe!$B:$B,$B10,Detalhe!$C:$C,$C10,Detalhe!$H:$H,$D10,Detalhe!$F:$F,"Ações") | F10: =IF(E10=0,0,G10/E10) | G10: =SUMIFS(Detalhe!$L:$L,Detalhe!$D:$D,"Empresa",Detalhe!$B:$B,$B10,Detalhe!$C:$C,$C10,Detalhe!$H:$H,$D10,Detalhe!$F:$F,"Ações")
A11: Yduqs | B11: YDUQ3 | C11: 46143 | D11: Compra | E11: =SUMIFS(Detalhe!$J:$J,Detalhe!$D:$D,"Empresa",Detalhe!$B:$B,$B11,Detalhe!$C:$C,$C11,Detalhe!$H:$H,$D11,Detalhe!$F:$F,"Ações") | F11: =IF(E11=0,0,G11/E11) | G11: =SUMIFS(Detalhe!$L:$L,Detalhe!$D:$D,"Empresa",Detalhe!$B:$B,$B11,Detalhe!$C:$C,$C11,Detalhe!$H:$H,$D11,Detalhe!$F:$F,"Ações")
A12: Yduqs | B12: YDUQ3 | C12: 46113 | D12: Compra | E12: =SUMIFS(Detalhe!$J:$J,Detalhe!$D:$D,"Empresa",Detalhe!$B:$B,$B12,Detalhe!$C:$C,$C12,Detalhe!$H:$H,$D12,Detalhe!$F:$F,"Ações") | F12: =IF(E12=0,0,G12/E12) | G12: =SUMIFS(Detalhe!$L:$L,Detalhe!$D:$D,"Empresa",Detalhe!$B:$B,$B12,Detalhe!$C:$C,$C12,Detalhe!$H:$H,$D12,Detalhe!$F:$F,"Ações")
A13: Fleury | B13: FLRY3 | C13: 46082 | D13: Compra | E13: =SUMIFS(Detalhe!$J:$J,Detalhe!$D:$D,"Empresa",Detalhe!$B:$B,$B13,Detalhe!$C:$C,$C13,Detalhe!$H:$H,$D13,Detalhe!$F:$F,"Ações") | F13: =IF(E13=0,0,G13/E13) | G13: =SUMIFS(Detalhe!$L:$L,Detalhe!$D:$D,"Empresa",Detalhe!$B:$B,$B13,Detalhe!$C:$C,$C13,Detalhe!$H:$H,$D13,Detalhe!$F:$F,"Ações")
... A77: Yduqs | B77: YDUQ3 | C77: 45566 | D77: Compra | E77: =SUMIFS(Detalhe!$J:$J,Detalhe!$D:$D,"Empresa",Detalhe!$B:$B,$B77,Detalhe!$C:$C,$C77,Detalhe!$H:$H,$D77,Detalhe!$F:$F,"Ações") | F77: =IF(E77=0,0,G77/E77) | G77: =SUMIFS(Detalhe!$L:$L,Detalhe!$D:$D,"Empresa",Detalhe!$B:$B,$B77,Detalhe!$C:$C,$C77,Detalhe!$H:$H,$D77,Detalhe!$F:$F,"Ações")

Sheet Controladores
A1: Empresa | B1: Ticker | C1: Mês e ano | D1: Operação | E1: Qtd movimentada | F1: Preço médio (R$) | G1: Valor total (R$)
A2: Mater Dei | B2: MATD3 | C2: 46266 | D2: Venda | E2: =SUMIFS(Detalhe!$J:$J,Detalhe!$D:$D,"Controladores",Detalhe!$B:$B,$B2,Detalhe!$C:$C,$C2,Detalhe!$H:$H,$D2,Detalhe!$F:$F,"Ações") | F2: =IF(E2=0,0,G2/E2) | G2: =SUMIFS(Detalhe!$L:$L,Detalhe!$D:$D,"Controladores",Detalhe!$B:$B,$B2,Detalhe!$C:$C,$C2,Detalhe!$H:$H,$D2,Detalhe!$F:$F,"Ações")
A3: Ânima | B3: ANIM3 | C3: 46266 | D3: Compra | E3: =SUMIFS(Detalhe!$J:$J,Detalhe!$D:$D,"Controladores",Detalhe!$B:$B,$B3,Detalhe!$C:$C,$C3,Detalhe!$H:$H,$D3,Detalhe!$F:$F,"Ações") | F3: =IF(E3=0,0,G3/E3) | G3: =SUMIFS(Detalhe!$L:$L,Detalhe!$D:$D,"Controladores",Detalhe!$B:$B,$B3,Detalhe!$C:$C,$C3,Detalhe!$H:$H,$D3,Detalhe!$F:$F,"Ações")
A4: Hapvida | B4: HAPV3 | C4: 46235 | D4: Compra | E4: =SUMIFS(Detalhe!$J:$J,Detalhe!$D:$D,"Controladores",Detalhe!$B:$B,$B4,Detalhe!$C:$C,$C4,Detalhe!$H:$H,$D4,Detalhe!$F:$F,"Ações") | F4: =IF(E4=0,0,G4/E4) | G4: =SUMIFS(Detalhe!$L:$L,Detalhe!$D:$D,"Controladores",Detalhe!$B:$B,$B4,Detalhe!$C:$C,$C4,Detalhe!$H:$H,$D4,Detalhe!$F:$F,"Ações")
A5: Mater Dei | B5: MATD3 | C5: 46235 | D5: Venda | E5: =SUMIFS(Detalhe!$J:$J,Detalhe!$D:$D,"Controladores",Detalhe!$B:$B,$B5,Detalhe!$C:$C,$C5,Detalhe!$H:$H,$D5,Detalhe!$F:$F,"Ações") | F5: =IF(E5=0,0,G5/E5) | G5: =SUMIFS(Detalhe!$L:$L,Detalhe!$D:$D,"Controladores",Detalhe!$B:$B,$B5,Detalhe!$C:$C,$C5,Detalhe!$H:$H,$D5,Detalhe!$F:$F,"Ações")
A6: Ânima | B6: ANIM3 | C6: 46235 | D6: Compra | E6: =SUMIFS(Detalhe!$J:$J,Detalhe!$D:$D,"Controladores",Detalhe!$B:$B,$B6,Detalhe!$C:$C,$C6,Detalhe!$H:$H,$D6,Detalhe!$F:$F,"Ações") | F6: =IF(E6=0,0,G6/E6) | G6: =SUMIFS(Detalhe!$L:$L,Detalhe!$D:$D,"Controladores",Detalhe!$B:$B,$B6,Detalhe!$C:$C,$C6,Detalhe!$H:$H,$D6,Detalhe!$F:$F,"Ações")
A7: Hypera | B7: HYPE3 | C7: 46204 | D7: Compra | E7: =SUMIFS(Detalhe!$J:$J,Detalhe!$D:$D,"Controladores",Detalhe!$B:$B,$B7,Detalhe!$C:$C,$C7,Detalhe!$H:$H,$D7,Detalhe!$F:$F,"Ações") | F7: =IF(E7=0,0,G7/E7) | G7: =SUMIFS(Detalhe!$L:$L,Detalhe!$D:$D,"Controladores",Detalhe!$B:$B,$B7,Detalhe!$C:$C,$C7,Detalhe!$H:$H,$D7,Detalhe!$F:$F,"Ações")
A8: Rede D'Or | B8: RDOR3 | C8: 46204 | D8: Compra | E8: =SUMIFS(Detalhe!$J:$J,Detalhe!$D:$D,"Controladores",Detalhe!$B:$B,$B8,Detalhe!$C:$C,$C8,Detalhe!$H:$H,$D8,Detalhe!$F:$F,"Ações") | F8: =IF(E8=0,0,G8/E8) | G8: =SUMIFS(Detalhe!$L:$L,Detalhe!$D:$D,"Controladores",Detalhe!$B:$B,$B8,Detalhe!$C:$C,$C8,Detalhe!$H:$H,$D8,Detalhe!$F:$F,"Ações")
A9: Ânima | B9: ANIM3 | C9: 46204 | D9: Compra | E9: =SUMIFS(Detalhe!$J:$J,Detalhe!$D:$D,"Controladores",Detalhe!$B:$B,$B9,Detalhe!$C:$C,$C9,Detalhe!$H:$H,$D9,Detalhe!$F:$F,"Ações") | F9: =IF(E9=0,0,G9/E9) | G9: =SUMIFS(Detalhe!$L:$L,Detalhe!$D:$D,"Controladores",Detalhe!$B:$B,$B9,Detalhe!$C:$C,$C9,Detalhe!$H:$H,$D9,Detalhe!$F:$F,"Ações")
A10: Hypera | B10: HYPE3 | C10: 46174 | D10: Compra | E10: =SUMIFS(Detalhe!$J:$J,Detalhe!$D:$D,"Controladores",Detalhe!$B:$B,$B10,Detalhe!$C:$C,$C10,Detalhe!$H:$H,$D10,Detalhe!$F:$F,"Ações") | F10: =IF(E10=0,0,G10/E10) | G10: =SUMIFS(Detalhe!$L:$L,Detalhe!$D:$D,"Controladores",Detalhe!$B:$B,$B10,Detalhe!$C:$C,$C10,Detalhe!$H:$H,$D10,Detalhe!$F:$F,"Ações")
A11: Mater Dei | B11: MATD3 | C11: 46174 | D11: Venda | E11: =SUMIFS(Detalhe!$J:$J,Detalhe!$D:$D,"Controladores",Detalhe!$B:$B,$B11,Detalhe!$C:$C,$C11,Detalhe!$H:$H,$D11,Detalhe!$F:$F,"Ações") | F11: =IF(E11=0,0,G11/E11) | G11: =SUMIFS(Detalhe!$L:$L,Detalhe!$D:$D,"Controladores",Detalhe!$B:$B,$B11,Detalhe!$C:$C,$C11,Detalhe!$H:$H,$D11,Detalhe!$F:$F,"Ações")
A12: Rede D'Or | B12: RDOR3 | C12: 46174 | D12: Compra | E12: =SUMIFS(Detalhe!$J:$J,Detalhe!$D:$D,"Controladores",Detalhe!$B:$B,$B12,Detalhe!$C:$C,$C12,Detalhe!$H:$H,$D12,Detalhe!$F:$F,"Ações") | F12: =IF(E12=0,0,G12/E12) | G12: =SUMIFS(Detalhe!$L:$L,Detalhe!$D:$D,"Controladores",Detalhe!$B:$B,$B12,Detalhe!$C:$C,$C12,Detalhe!$H:$H,$D12,Detalhe!$F:$F,"Ações")
A13: Hypera | B13: HYPE3 | C13: 46143 | D13: Compra | E13: =SUMIFS(Detalhe!$J:$J,Detalhe!$D:$D,"Controladores",Detalhe!$B:$B,$B13,Detalhe!$C:$C,$C13,Detalhe!$H:$H,$D13,Detalhe!$F:$F,"Ações") | F13: =IF(E13=0,0,G13/E13) | G13: =SUMIFS(Detalhe!$L:$L,Detalhe!$D:$D,"Controladores",Detalhe!$B:$B,$B13,Detalhe!$C:$C,$C13,Detalhe!$H:$H,$D13,Detalhe!$F:$F,"Ações")
... A33: Rede D'Or | B33: RDOR3 | C33: 45597 | D33: Compra | E33: =SUMIFS(Detalhe!$J:$J,Detalhe!$D:$D,"Controladores",Detalhe!$B:$B,$B33,Detalhe!$C:$C,$C33,Detalhe!$H:$H,$D33,Detalhe!$F:$F,"Ações") | F33: =IF(E33=0,0,G33/E33) | G33: =SUMIFS(Detalhe!$L:$L,Detalhe!$D:$D,"Controladores",Detalhe!$B:$B,$B33,Detalhe!$C:$C,$C33,Detalhe!$H:$H,$D33,Detalhe!$F:$F,"Ações")

Sheet Administradores
A1: Empresa | B1: Ticker | C1: Mês e ano | D1: Operação | E1: Qtd movimentada | F1: Preço médio (R$) | G1: Valor total (R$)
A2: Blau | B2: BLAU3 | C2: 46266 | D2: Compra | E2: =SUMIFS(Detalhe!$J:$J,Detalhe!$D:$D,"Administradores",Detalhe!$B:$B,$B2,Detalhe!$C:$C,$C2,Detalhe!$H:$H,$D2,Detalhe!$F:$F,"Ações") | F2: =IF(E2=0,0,G2/E2) | G2: =SUMIFS(Detalhe!$L:$L,Detalhe!$D:$D,"Administradores",Detalhe!$B:$B,$B2,Detalhe!$C:$C,$C2,Detalhe!$H:$H,$D2,Detalhe!$F:$F,"Ações")
A3: Cogna | B3: COGN3 | C3: 46266 | D3: Venda | E3: =SUMIFS(Detalhe!$J:$J,Detalhe!$D:$D,"Administradores",Detalhe!$B:$B,$B3,Detalhe!$C:$C,$C3,Detalhe!$H:$H,$D3,Detalhe!$F:$F,"Ações") | F3: =IF(E3=0,0,G3/E3) | G3: =SUMIFS(Detalhe!$L:$L,Detalhe!$D:$D,"Administradores",Detalhe!$B:$B,$B3,Detalhe!$C:$C,$C3,Detalhe!$H:$H,$D3,Detalhe!$F:$F,"Ações")
A4: Fleury | B4: FLRY3 | C4: 46266 | D4: Venda | E4: =SUMIFS(Detalhe!$J:$J,Detalhe!$D:$D,"Administradores",Detalhe!$B:$B,$B4,Detalhe!$C:$C,$C4,Detalhe!$H:$H,$D4,Detalhe!$F:$F,"Ações") | F4: =IF(E4=0,0,G4/E4) | G4: =SUMIFS(Detalhe!$L:$L,Detalhe!$D:$D,"Administradores",Detalhe!$B:$B,$B4,Detalhe!$C:$C,$C4,Detalhe!$H:$H,$D4,Detalhe!$F:$F,"Ações")
A5: Hypera | B5: HYPE3 | C5: 46266 | D5: Venda | E5: =SUMIFS(Detalhe!$J:$J,Detalhe!$D:$D,"Administradores",Detalhe!$B:$B,$B5,Detalhe!$C:$C,$C5,Detalhe!$H:$H,$D5,Detalhe!$F:$F,"Ações") | F5: =IF(E5=0,0,G5/E5) | G5: =SUMIFS(Detalhe!$L:$L,Detalhe!$D:$D,"Administradores",Detalhe!$B:$B,$B5,Detalhe!$C:$C,$C5,Detalhe!$H:$H,$D5,Detalhe!$F:$F,"Ações")
A6: Oncoclínicas | B6: ONCO3 | C6: 46266 | D6: Venda | E6: =SUMIFS(Detalhe!$J:$J,Detalhe!$D:$D,"Administradores",Detalhe!$B:$B,$B6,Detalhe!$C:$C,$C6,Detalhe!$H:$H,$D6,Detalhe!$F:$F,"Ações") | F6: =IF(E6=0,0,G6/E6) | G6: =SUMIFS(Detalhe!$L:$L,Detalhe!$D:$D,"Administradores",Detalhe!$B:$B,$B6,Detalhe!$C:$C,$C6,Detalhe!$H:$H,$D6,Detalhe!$F:$F,"Ações")
A7: Cogna | B7: COGN3 | C7: 46235 | D7: Venda | E7: =SUMIFS(Detalhe!$J:$J,Detalhe!$D:$D,"Administradores",Detalhe!$B:$B,$B7,Detalhe!$C:$C,$C7,Detalhe!$H:$H,$D7,Detalhe!$F:$F,"Ações") | F7: =IF(E7=0,0,G7/E7) | G7: =SUMIFS(Detalhe!$L:$L,Detalhe!$D:$D,"Administradores",Detalhe!$B:$B,$B7,Detalhe!$C:$C,$C7,Detalhe!$H:$H,$D7,Detalhe!$F:$F,"Ações")
A8: Fleury | B8: FLRY3 | C8: 46235 | D8: Venda | E8: =SUMIFS(Detalhe!$J:$J,Detalhe!$D:$D,"Administradores",Detalhe!$B:$B,$B8,Detalhe!$C:$C,$C8,Detalhe!$H:$H,$D8,Detalhe!$F:$F,"Ações") | F8: =IF(E8=0,0,G8/E8) | G8: =SUMIFS(Detalhe!$L:$L,Detalhe!$D:$D,"Administradores",Detalhe!$B:$B,$B8,Detalhe!$C:$C,$C8,Detalhe!$H:$H,$D8,Detalhe!$F:$F,"Ações")
A9: Hapvida | B9: HAPV3 | C9: 46235 | D9: Compra | E9: =SUMIFS(Detalhe!$J:$J,Detalhe!$D:$D,"Administradores",Detalhe!$B:$B,$B9,Detalhe!$C:$C,$C9,Detalhe!$H:$H,$D9,Detalhe!$F:$F,"Ações") | F9: =IF(E9=0,0,G9/E9) | G9: =SUMIFS(Detalhe!$L:$L,Detalhe!$D:$D,"Administradores",Detalhe!$B:$B,$B9,Detalhe!$C:$C,$C9,Detalhe!$H:$H,$D9,Detalhe!$F:$F,"Ações")
A10: Hypera | B10: HYPE3 | C10: 46235 | D10: Compra | E10: =SUMIFS(Detalhe!$J:$J,Detalhe!$D:$D,"Administradores",Detalhe!$B:$B,$B10,Detalhe!$C:$C,$C10,Detalhe!$H:$H,$D10,Detalhe!$F:$F,"Ações") | F10: =IF(E10=0,0,G10/E10) | G10: =SUMIFS(Detalhe!$L:$L,Detalhe!$D:$D,"Administradores",Detalhe!$B:$B,$B10,Detalhe!$C:$C,$C10,Detalhe!$H:$H,$D10,Detalhe!$F:$F,"Ações")
A11: Hypera | B11: HYPE3 | C11: 46235 | D11: Venda | E11: =SUMIFS(Detalhe!$J:$J,Detalhe!$D:$D,"Administradores",Detalhe!$B:$B,$B11,Detalhe!$C:$C,$C11,Detalhe!$H:$H,$D11,Detalhe!$F:$F,"Ações") | F11: =IF(E11=0,0,G11/E11) | G11: =SUMIFS(Detalhe!$L:$L,Detalhe!$D:$D,"Administradores",Detalhe!$B:$B,$B11,Detalhe!$C:$C,$C11,Detalhe!$H:$H,$D11,Detalhe!$F:$F,"Ações")
A12: Hypera | B12: HYPE3 | C12: 46204 | D12: Venda | E12: =SUMIFS(Detalhe!$J:$J,Detalhe!$D:$D,"Administradores",Detalhe!$B:$B,$B12,Detalhe!$C:$C,$C12,Detalhe!$H:$H,$D12,Detalhe!$F:$F,"Ações") | F12: =IF(E12=0,0,G12/E12) | G12: =SUMIFS(Detalhe!$L:$L,Detalhe!$D:$D,"Administradores",Detalhe!$B:$B,$B12,Detalhe!$C:$C,$C12,Detalhe!$H:$H,$D12,Detalhe!$F:$F,"Ações")
A13: Ânima | B13: ANIM3 | C13: 46204 | D13: Compra | E13: =SUMIFS(Detalhe!$J:$J,Detalhe!$D:$D,"Administradores",Detalhe!$B:$B,$B13,Detalhe!$C:$C,$C13,Detalhe!$H:$H,$D13,Detalhe!$F:$F,"Ações") | F13: =IF(E13=0,0,G13/E13) | G13: =SUMIFS(Detalhe!$L:$L,Detalhe!$D:$D,"Administradores",Detalhe!$B:$B,$B13,Detalhe!$C:$C,$C13,Detalhe!$H:$H,$D13,Detalhe!$F:$F,"Ações")
... A85: TIM | B85: TIMS3 | C85: 45566 | D85: Venda | E85: =SUMIFS(Detalhe!$J:$J,Detalhe!$D:$D,"Administradores",Detalhe!$B:$B,$B85,Detalhe!$C:$C,$C85,Detalhe!$H:$H,$D85,Detalhe!$F:$F,"Ações") | F85: =IF(E85=0,0,G85/E85) | G85: =SUMIFS(Detalhe!$L:$L,Detalhe!$D:$D,"Administradores",Detalhe!$B:$B,$B85,Detalhe!$C:$C,$C85,Detalhe!$H:$H,$D85,Detalhe!$F:$F,"Ações")

Sheet Detalhe
A1: Empresa | B1: Ticker | C1: Mês e ano | D1: Aba | E1: Grupo / qualificação | F1: Valor mobiliário | G1: Descrição no formulário | H1: Operação | I1: Dia | J1: Quantidade | K1: Preço (R$) | L1: Volume (R$) | M1: Protocolo | N1: Documento
A2: Blau | B2: BLAU3 | C2: 46266 | D2: Administradores | E2: Diretoria | F2: Ações | G2: Ações ON Itaú Compra à vista | H2: Compra | I2: 22 | J2: 500 | K2: 10.5 | L2: 5250 | M2: 1576098 | N2: abrir
A3: Cogna | B3: COGN3 | C3: 46266 | D3: Administradores | E3: Diretoria | F3: Ações | G3: Ações ON Ágora Investimentos Venda à vista | H3: Venda | I3: 2 | J3: 8150 | K3: 2.43 | L3: 19804.5 | M3: 1575605 | N3: abrir
A4: Cogna | B4: COGN3 | C4: 46266 | D4: Empresa | E4: (qualificação em branco) — COGNA EDUCAÇÃO S.A. | F4: Ações | G4: Ações ON Ágora Investimentos TRANSFERENCIA DE ACOES NO PERIODO DE VESTING | H4: Outros | I4: 17 | J4: 263207 | K4: 0.01 | L4: 2632.07 | M4: 1575598 | N4: abrir
A5: Cogna | B5: COGN3 | C5: 46266 | D5: Outros | E5: Órgãos Técnicos ou Consultivos | F5: Ações | G5: Ações ON Itaú Corretora de Valores S/A Compra à vista | H5: Compra | I5: 24 | J5: 100000 | K5: 2.25 | L5: 225000 | M5: 1575605 | N5: abrir
A6: Cogna | B6: COGN3 | C6: 46266 | D6: Outros | E6: Órgãos Técnicos ou Consultivos | F6: Ações | G6: Ações ON Itaú Corretora de Valores S/A Compra à vista | H6: Compra | I6: 24 | J6: 100000 | K6: 2.2 | L6: 220000 | M6: 1575605 | N6: abrir
A7: Cogna | B7: COGN3 | C7: 46266 | D7: Outros | E7: Órgãos Técnicos ou Consultivos | F7: Ações | G7: Ações ON Itaú Corretora de Valores S/A Compra à vista | H7: Compra | I7: 25 | J7: 100000 | K7: 2.15 | L7: 215000 | M7: 1575605 | N7: abrir
A8: Fleury | B8: FLRY3 | C8: 46266 | D8: Administradores | E8: Diretoria | F8: Ações | G8: Ações ON Agora Venda à vista | H8: Venda | I8: 2 | J8: 60000 | K8: 19.15959 | L8: 1149575.1 | M8: 1576463 | N8: abrir
A9: Fleury | B9: FLRY3 | C9: 46266 | D9: Administradores | E9: Diretoria | F9: Ações | G9: Ações ON Agora Venda à vista | H9: Venda | I9: 3 | J9: 10000 | K9: 19.945 | L9: 199450 | M9: 1576463 | N9: abrir
A10: Fleury | B10: FLRY3 | C10: 46266 | D10: Administradores | E10: Diretoria | F10: Ações | G10: Ações ON Agora Venda à vista | H10: Venda | I10: 4 | J10: 5000 | K10: 20.23 | L10: 101150 | M10: 1576463 | N10: abrir
A11: Fleury | B11: FLRY3 | C11: 46266 | D11: Administradores | E11: Diretoria | F11: Ações | G11: Ações ON Agora Venda à vista | H11: Venda | I11: 11 | J11: 50000 | K11: 21.13366 | L11: 1056682.9 | M11: 1576463 | N11: abrir
A12: Hapvida | B12: HAPV3 | C12: 46266 | D12: Controladores | E12: Controlador | F12: Ações | G12: Ações ON Banco BTG Pactual RECEBIMENTO DE AÇÕES POR LIQUIDAÇÃO DO SWAP | H12: Outros | I12: 15 | J12: 350412 | K12: 6.49 | L12: 2274173.9 | M12: 1576091 | N12: abrir
A13: Hapvida | B13: HAPV3 | C13: 46266 | D13: Controladores | E13: Controlador | F13: Derivativos | G13: Derivativos SWAP LIQUIDACAO FISICA Banco BTG Pactual LIQUIDAÇÃO PARCIAL DO SWAP | H13: Outros | I13: 15 | J13: 350412 | K13: 6.49 | L13: 2274173.9 | M13: 1576091 | N13: abrir
... A2157: Yduqs | B2157: YDUQ3 | C2157: 45566 | D2157: Empresa | E2157: Companhia - Tesouraria — ESTACIO PARTICIPAÇÕES SA | F2157: Ações | G2157: Ações ON XP RECOMPRA DE ACOES | H2157: Compra | I2157: 22 | J2157: 267000 | K2157: 10.42872 | L2157: 2784469 | M2157: 1301309 | N2157: abrir

Sheet Documentos
A1: Empresa | B1: Ticker | C1: Mês e ano | D1: Formulário | E1: Protocolo | F1: Versão | G1: Apresentação | H1: Entrega | I1: Situação | J1: Operações lidas | K1: Conferência de saldo | L1: Documento
A2: Blau | B2: BLAU3 | C2: 46266 | D2: Consolidado | E2: 1576098 | F2: 1 | G2: Apresentação | H2: 2026-10-09 17:11 | I2: Vigente | J2: 1 | K2: OK | L2: abrir
A3: Blau | B3: BLAU3 | C3: 46266 | D3: Individual | E3: 1576092 | F3: 1 | G3: Apresentação | H3: 2026-10-09 17:10 | I3: Vigente | J3: 0 | K3: OK | L3: abrir
A4: Cogna | B4: COGN3 | C4: 46266 | D4: Consolidado | E4: 1575605 | F4: 1 | G4: Apresentação | H4: 2026-10-08 18:13 | I4: Vigente | J4: 4 | K4: OK | L4: abrir
A5: Cogna | B5: COGN3 | C5: 46266 | D5: Individual | E5: 1575598 | F5: 1 | G5: Apresentação | H5: 2026-10-08 18:08 | I5: Vigente | J5: 1 | K5: OK* (qualificação em branco): saldo final -263.207 ações vs. compras/vendas (coberto por operações não-mercado) | L5: abrir
A6: Dasa | B6: DASA3 | C6: 46266 | D6: Consolidado | E6: 1576259 | F6: 1 | G6: Apresentação | H6: 2026-10-09 18:08 | I6: Vigente | J6: 0 | K6: OK | L6: abrir
A7: Dasa | B7: DASA3 | C7: 46266 | D7: Individual | E7: 1576257 | F7: 1 | G7: Apresentação | H7: 2026-10-09 18:08 | I7: Vigente | J7: 0 | K7: OK | L7: abrir
A8: Fleury | B8: FLRY3 | C8: 46266 | D8: Consolidado | E8: 1576463 | F8: 1 | G8: Apresentação | H8: 2026-10-10 14:25 | I8: Vigente | J8: 4 | K8: OK | L8: abrir
A9: Fleury | B9: FLRY3 | C9: 46266 | D9: Individual | E9: 1576462 | F9: 1 | G9: Apresentação | H9: 2026-10-10 14:22 | I9: Vigente | J9: 0 | K9: OK | L9: abrir
A10: Hapvida | B10: HAPV3 | C10: 46266 | D10: Consolidado | E10: 1576091 | F10: 1 | G10: Apresentação | H10: 2026-10-09 17:10 | I10: Vigente | J10: 16 | K10: OK* Controlador: saldo final +1.754.204 ações vs. compras/vendas (coberto por operações não-mercado) | L10: abrir
A11: Hapvida | B11: HAPV3 | C11: 46266 | D11: Individual | K11: NÃO ENCONTRADO (prazo: 10 dias após o fim do mês)
A12: Hypera | B12: HYPE3 | C12: 46266 | D12: Consolidado | E12: 1576233 | F12: 1 | G12: Apresentação | H12: 2026-10-09 18:02 | I12: Vigente | J12: 10 | K12: OK | L12: abrir
A13: Hypera | B13: HYPE3 | C13: 46266 | D13: Individual | E13: 1576220 | F13: 1 | G13: Apresentação | H13: 2026-10-09 18:00 | I13: Vigente | J13: 0 | K13: OK | L13: abrir
A14: Mater Dei | B14: MATD3 | C14: 46266 | D14: Consolidado | E14: 1574949 | F14: 1 | G14: Apresentação | H14: 2026-10-07 09:51 | I14: Vigente | J14: 3 | K14: OK | L14: abrir
A15: Mater Dei | B15: MATD3 | C15: 46266 | D15: Individual | E15: 1574503 | F15: 1 | G15: Apresentação | H15: 2026-10-05 19:39 | I15: Vigente | J15: 2 | K15: OK | L15: abrir
A16: Odontoprev | B16: ODPV3 | C16: 46266 | D16: Consolidado | E16: 1575479 | F16: 1 | G16: Apresentação | H16: 2026-10-08 17:09 | I16: Vigente | J16: 0 | K16: OK | L16: abrir
A17: Odontoprev | B17: ODPV3 | C17: 46266 | D17: Individual | E17: 1575475 | F17: 1 | G17: Apresentação | H17: 2026-10-08 17:08 | I17: Vigente | J17: 0 | K17: OK | L17: abrir
A18: Oncoclínicas | B18: ONCO3 | C18: 46266 | D18: Consolidado | E18: 1576276 | F18: 1 | G18: Apresentação | H18: 2026-10-09 18:21 | I18: Vigente | J18: 1 | K18: OK | L18: abrir
A19: Oncoclínicas | B19: ONCO3 | C19: 46266 | D19: Individual | E19: 1576021 | F19: 1 | G19: Apresentação | H19: 2026-10-09 16:35 | I19: Vigente | J19: 0 | K19: OK | L19: abrir
A20: Qualicorp | B20: QUAL3 | C20: 46266 | D20: Consolidado | E20: 1574849 | F20: 1 | G20: Apresentação | H20: 2026-10-06 18:46 | I20: Vigente | J20: 0 | K20: OK | L20: abrir
A21: Qualicorp | B21: QUAL3 | C21: 46266 | D21: Individual | E21: 1574846 | F21: 1 | G21: Apresentação | H21: 2026-10-06 18:44 | I21: Vigente | J21: 0 | K21: OK | L21: abrir
A22: Rede D'Or | B22: RDOR3 | C22: 46266 | D22: Consolidado | E22: 1576329 | F22: 1 | G22: Apresentação | H22: 2026-10-09 18:36 | I22: Vigente | J22: 0 | K22: OK | L22: abrir
A23: Rede D'Or | B23: RDOR3 | C23: 46266 | D23: Individual | E23: 1576320 | F23: 1 | G23: Apresentação | H23: 2026-10-09 18:35 | I23: Vigente | J23: 0 | K23: OK | L23: abrir
... A757: Ânima | B757: ANIM3 | C757: 45566 | D757: Individual | E757: 1302179 | F757: 1 | G757: Apresentação | H757: 2024-11-11 | I757: Vigente | J757: 0 | K757: OK | L757: abrir

Sheet Leia-me
A1: Recompras (empresa) e negociações de controladores e administradores — CVM
A2: Gerado em 14/10/2026 14:06 por buybacks_cvm.py (meses de referência a partir de 10/2024).
A4: FONTE: formulários mensais 'Valores Mobiliários Negociados e Detidos' (art. 11 da Res. CVM 44) entregues à CVM. Lista de documentos: dados abertos da CVM (dados.cvm.gov.br, IPE) + consulta ao RAD dos últimos dias.
A6: ABAS
A7: Empresa — formulário 'Posição Individual': a própria companhia (tesouraria) e controladas. Compra = recompra; venda = alienação de ações em tesouraria no mercado.
A8: Controladores — formulário 'Posição Consolidada', grupo Controlador.
A9: Administradores — formulário 'Posição Consolidada', grupos Conselho de Administração + Diretoria (Lei 6.404). Conselho Fiscal e Órgãos Técnicos ficam em Detalhe (Aba = Outros).
A10: Detalhe — uma linha por operação lida de cada documento vigente, inclusive as que não entram nos resumos.
A11: Documentos — todos os documentos encontrados, reapresentações substituídas, documentos ainda não entregues e a conferência de saldo de cada um.
A13: REGRAS
A14: 1. Só AÇÕES negociadas no mercado (compra/venda à vista ou a termo) entram nos resumos. Vesting/ILP, liquidação de swap, empréstimo de ações, subscrição, bonificação, posse/saída de cargo, debêntures, opções e ADRs ficam só em Detalhe.
A15: 2. Compra/venda declarada sem preço vira 'Compra s/ preço' / 'Venda s/ preço': aparece em Detalhe e fecha a conferência de saldo, mas fica fora de Qtd, Valor e Preço médio. Par 'compra a termo' + 'venda à vista' no mesmo dia e quantidade vira 'Rolagem a termo' (a posição não muda) e também fica fora dos resumos.
... A21: ATUALIZAR: py buybacks_cvm.py (ver README.md, seção 'Planilha de recompras e insiders').
